{
    "base": {
        "data": {
            "deny": {
                "Upgradeable": 0
            },
            "require": {}
        },
        "item": "minecraft:iron_hoe"
    },
    "ingredient": {
        "data": {
            "require": {}
        },
        "item": "minecraft:diamond"
    },
    "result": {
        "data": {
            "$": "$base",
            "Damage": "$390"
        },
        "item": "minecraft:diamond_hoe"
    },
    "type": "nbtcrafting:smithing"
}