{
  "settings": {
    "hidden": "IN_PROGRESS"
  },
  "dependencies": [
    "423E897DEB76653D"
  ],
  "tasks": {
    "64AA0C69C81F13E5": {
      "type": "heracles:item",
      "amount": 32,
      "item": "minecraft:rail"
    }
  },
  "rewards": {
    "66BC7E72767B1509": {
      "type": "heracles:item",
      "item": {
        "id": "minecraft:magenta_glazed_terracotta",
        "count": 8
      }
    },
    "36F053E83568DB0C": {
      "type": "heracles:item",
      "item": {
        "id": "minecraft:powered_rail",
        "count": 8
      }
    },
    "4E9F3C7796CE03C2": {
      "type": "heracles:item",
      "item": {
        "id": "minecraft:redstone_torch",
        "count": 8
      }
    },
    "4EFAEFD4C85ABCC9": {
      "type": "heracles:item",
      "item": {
        "id": "minecraft:minecart"
      }
    },
    "723355EEC64996EC": {
      "type": "heracles:item",
      "item": {
        "id": "minecraft:detector_rail",
        "count": 2
      }
    },
    "5B9889C5B7BB26F8": {
      "type": "heracles:item",
      "item": {
        "id": "minecraft:rail",
        "count": 64
      }
    },
    "07C3FFE36ED0CBEB": {
      "type": "heracles:item",
      "item": {
        "id": "minecraft:furnace_minecart"
      }
    }
  },
  "display": {
    "title": "Invention of Rail",
    "description": [
      "<subtitle id=\"0EF299A1A5009971\" bold=\"true\" centered=\"true\" color=\"lightgray\"/>",
      "<hr/>",
      "<task task=\"64AA0C69C81F13E5\" quest=\"0EF299A1A5009971\"/>",
      "<hr/>",
      "&&3Minecarts and rails&&r can be used to build &&deasy transit&&r between known locations.",
      "<br/>",
      "Just set the rail down, place down a minecart, and hop in!",
      "<br/>",
      "Minecarts &&3can't go up steep hills without a push&&r. Try using a &&ePowered Rail&&r with a redstone torch, or a &&eFurnace Minecart&&r with fuel!",
      "<br/>",
      "&&eDetector Rails&&r can be used to &&dtrigger redstone circuits&&r when passed by. Try it out!",
      "<br/>",
      "&&7[Fabrication]&&r &&eMagenta Glazed Terracotta&&r under a &&3Powered Rail&&r will make it &&ddirectional&&r - great for loading new carts onto a rail!",
      "<hr/>",
      "<reward reward=\"66BC7E72767B1509\" quest=\"0EF299A1A5009971\"/>",
      "<reward reward=\"36F053E83568DB0C\" quest=\"0EF299A1A5009971\"/>",
      "<reward reward=\"4E9F3C7796CE03C2\" quest=\"0EF299A1A5009971\"/>",
      "<reward reward=\"4EFAEFD4C85ABCC9\" quest=\"0EF299A1A5009971\"/>",
      "<reward reward=\"723355EEC64996EC\" quest=\"0EF299A1A5009971\"/>",
      "<reward reward=\"5B9889C5B7BB26F8\" quest=\"0EF299A1A5009971\"/>",
      "<reward reward=\"07C3FFE36ED0CBEB\" quest=\"0EF299A1A5009971\"/>"
    ],
    "icon": {
      "type": "heracles:item",
      "item": "minecraft:rail"
    },
    "icon_background": "heracles:textures/gui/quest_backgrounds/hexagons.png",
    "subtitle": {
      "text": "Gather some Rail materials"
    },
    "groups": {
      "Homesteading": {
        "position": [
          -208,
          -416
        ]
      }
    }
  }
}